{"_items": [{"cntr_short": "NL", "city": "Noordscheschut", "_updated": "Thu, 01 Jan 1970 00:00:00 GMT", "loc": [52.7237546, 6.5356], "text": "@DusDavid nee want je moet dan world of tanks spelen", "created_at": "Thu, 23 Apr 2015 06:07:31 +0000", "cntr_long": "Netherlands", "day_report": "23/3/2015", "_links": {"self": {"href": "twittertop/55388c2b591f90d13a8b4c88", "title": "Twittertop"}}, "loc_name": "Noordscheschut", "_created": "Thu, 01 Jan 1970 00:00:00 GMT", "_id": "55388c2b591f90d13a8b4c88", "_etag": "fb169c567e49cfd80f8ec4afa678ea6a2fbae559"}, {"cntr_short": "UA", "city": "Melitopol'", "_updated": "Thu, 01 Jan 1970 00:00:00 GMT", "loc": [46.833333, 35.366667], "text": "\u041c\u043d\u0435 \u043f\u043e\u043d\u0440\u0430\u0432\u0438\u043b\u043e\u0441\u044c \u0432\u0438\u0434\u0435\u043e \"\u0422\u0420\u0418 \u0421\u041f\u041e\u0421\u041e\u0411\u0410 \u041f\u041e\u041b\u0423\u0427\u0418\u0422\u042c \u0423\u0414\u041e\u0412\u041e\u041b\u042c\u0421\u0422\u0412\u0418\u0415 \u041e\u0422 WORLD OF TANKS, \u0410\u041d\u0410\u041b\u0418\u0417", "created_at": "Thu, 23 Apr 2015 06:07:23 +0000", "cntr_long": "Ukraine", "day_report": "23/3/2015", "_links": {"self": {"href": "twittertop/55388c2b591f90d13a8b4c86", "title": "Twittertop"}}, "loc_name": "Melitopol", "_created": "Thu, 01 Jan 1970 00:00:00 GMT", "_id": "55388c2b591f90d13a8b4c86", "_etag": "aaab800830b7abc6c0b2cda4126fccb9677bb7d5"}, {"cntr_short": "US", "city": "Norman", "_updated": "Thu, 01 Jan 1970 00:00:00 GMT", "loc": [35.2225668, -97.4394777], "text": "World of Tanks Blitz \u2013 \u0440\u0443\u0431\u0440\u0438\u043a\u0430 \u201c5 \u0431\u043e\u0435\u0432\u201d \u043d\u0430 \u0418\u0421-6 \u2013 WoT Blitz Android \u0438 iOS http://t.co/TAg6FQxPu1 #rtBYme", "created_at": "Thu, 23 Apr 2015 06:04:04 +0000", "cntr_long": "United States", "day_report": "23/3/2015", "_links": {"self": {"href": "twittertop/55388b7e9ad4ecf07b8b5dfb", "title": "Twittertop"}}, "loc_name": "Norman, OK", "_created": "Thu, 01 Jan 1970 00:00:00 GMT", "_id": "55388b7e9ad4ecf07b8b5dfb", "_etag": "ac39324927f8539f6b8cff0a1c6d38e04e3d5792"}, {"cntr_short": "GB", "city": " ", "_updated": "Thu, 01 Jan 1970 00:00:00 GMT", "loc": [55.378051, -3.435973], "text": "So, I\u2019m enjoying the World of Warships \u201cbeta\u201d and have begun to daydream of torpedoes and artillery.", "created_at": "Thu, 23 Apr 2015 06:03:35 +0000", "cntr_long": "United Kingdom", "day_report": "23/3/2015", "_links": {"self": {"href": "twittertop/55388b3b9ad4ecc7698b579c", "title": "Twittertop"}}, "loc_name": "UK", "_created": "Thu, 01 Jan 1970 00:00:00 GMT", "_id": "55388b3b9ad4ecc7698b579c", "_etag": "8058d02207b5b5dcf6a8c03a8288af997f8515e9"}, {"cntr_short": "RU", "city": "Kaliningrad", "_updated": "Thu, 01 Jan 1970 00:00:00 GMT", "loc": [54.716667, 20.516667], "text": "\u041c\u043d\u0435 \u043f\u043e\u043d\u0440\u0430\u0432\u0438\u043b\u043e\u0441\u044c \u0432\u0438\u0434\u0435\u043e \"[\u041f\u0430\u0442\u0447 0.9.7] \u041c\u043e\u0434\u041f\u0430\u043a \u043e\u0442 PRO\u0422\u0430\u043d\u043a\u0438 | \u041c\u041e\u0414\u043d\u044b\u0435 \u043d\u043e\u0432\u0438\u043d\u043a\u0438 World of Tanks\"", "created_at": "Thu, 23 Apr 2015 05:59:16 +0000", "cntr_long": "Russia", "day_report": "23/3/2015", "_links": {"self": {"href": "twittertop/55388a43591f90034a8b466d", "title": "Twittertop"}}, "loc_name": "Kaliningrad, Russia", "_created": "Thu, 01 Jan 1970 00:00:00 GMT", "_id": "55388a43591f90034a8b466d", "_etag": "ef6affaec7167638c57db16e71ff6303b864deb2"}, {"cntr_short": "US", "city": " ", "_updated": "Thu, 01 Jan 1970 00:00:00 GMT", "loc": [19.8967662, -155.5827818], "text": "World of Warships... HIEEE!!!! I'M A BETA TESTER!?\nI finally have time to post something!!!", "created_at": "Thu, 23 Apr 2015 05:57:48 +0000", "cntr_long": "United States", "day_report": "23/3/2015", "_links": {"self": {"href": "twittertop/553889e1591f9044388b62aa", "title": "Twittertop"}}, "loc_name": "Hawaii", "_created": "Thu, 01 Jan 1970 00:00:00 GMT", "_id": "553889e1591f9044388b62aa", "_etag": "815399daff604901ead249be75e40cdfab9bdfe3"}, {"cntr_short": "RU", "city": "Moscow", "_updated": "Thu, 01 Jan 1970 00:00:00 GMT", "loc": [55.755826, 37.6173], "text": "\u041f\u0430\u0442\u0447 9.7 \u0421\u0431\u043e\u0440\u043a\u0430 \u043b\u0443\u0447\u0448\u0438\u0445 \u043c\u043e\u0434\u043e\u0432 World of Tanks \u043e\u0442 AnTiNooB#wot #AnTiNooB #\u043c\u043e\u0434\u044b #\u0441\u0431\u043e\u0440\u043a\u0430=======... http://t.co/MbjrCaWU7o http://t.co/OWeTkbo5lH", "created_at": "Thu, 23 Apr 2015 05:49:31 +0000", "cntr_long": "Russia", "day_report": "23/3/2015", "_links": {"self": {"href": "twittertop/55388809591f908a7e8b5c56", "title": "Twittertop"}}, "loc_name": "\u041c\u043e\u0441\u043a\u0432\u0430", "_created": "Thu, 01 Jan 1970 00:00:00 GMT", "_id": "55388809591f908a7e8b5c56", "_etag": "52b3e8b2563431053ebbbe604db5975db8dd22f6"}, {"cntr_short": "US", "city": " ", "_updated": "Thu, 01 Jan 1970 00:00:00 GMT", "loc": [27.6648274, -81.5157535], "text": "World of Warships - First Time Playing!: http://t.co/5goxJImPbk via @YouTube", "created_at": "Thu, 23 Apr 2015 05:49:04 +0000", "cntr_long": "United States", "day_report": "23/3/2015", "_links": {"self": {"href": "twittertop/553887e5591f9007098b4bee", "title": "Twittertop"}}, "loc_name": "Florida", "_created": "Thu, 01 Jan 1970 00:00:00 GMT", "_id": "553887e5591f9007098b4bee", "_etag": "f68132afec8b13f70091341eed0181789be9764b"}, {"cntr_short": "RU", "city": "Moscow", "_updated": "Thu, 01 Jan 1970 00:00:00 GMT", "loc": [55.755826, 37.6173], "text": "\u0421\u0431\u043e\u0440\u043a\u0430 \u043c\u043e\u0434\u043e\u0432 \u043e\u0442 EXPROMT_MAX Full \u0434\u043b\u044f World of Tanks 0.9.7\u041e\u0431\u043d\u043e\u0432\u043b\u0435\u043d\u043e 22.04.2015 \u0434\u043e \u0432\u0435\u0440\u0441\u0438\u0438 (0... http://t.co/kNhlfcPRTq http://t.co/wEHSCCz2sz", "created_at": "Thu, 23 Apr 2015 05:48:46 +0000", "cntr_long": "Russia", "day_report": "23/3/2015", "_links": {"self": {"href": "twittertop/553887e5591f9007098b4bed", "title": "Twittertop"}}, "loc_name": "\u041c\u043e\u0441\u043a\u0432\u0430", "_created": "Thu, 01 Jan 1970 00:00:00 GMT", "_id": "553887e5591f9007098b4bed", "_etag": "165a6d366bff9a27a1890306732127794ade1343"}, {"cntr_short": "GB", "city": " ", "_updated": "Thu, 01 Jan 1970 00:00:00 GMT", "loc": [55.378051, -3.435973], "text": "About 10 hours into World of Warships, and first invocation to \u201cPKY\u201c. Longer than I thought.", "created_at": "Thu, 23 Apr 2015 05:46:55 +0000", "cntr_long": "United Kingdom", "day_report": "23/3/2015", "_links": {"self": {"href": "twittertop/55388763591f90a82a8b9fd9", "title": "Twittertop"}}, "loc_name": "UK", "_created": "Thu, 01 Jan 1970 00:00:00 GMT", "_id": "55388763591f90a82a8b9fd9", "_etag": "a26f946ca9d1d6f966163ff5851cfd39ac73ec03"}, {"cntr_short": "US", "city": "Birmingham", "_updated": "Thu, 01 Jan 1970 00:00:00 GMT", "loc": [33.5206608, -86.80248999999999], "text": "\u0421\u043e\u0432\u0435\u0442\u0441\u043a\u0438\u0439 \u0441\u043f\u043e\u0440\u0442 | \u0412 World of Tanks \u043f\u043e\u044f\u0432\u0438\u0442\u0441\u044f \u0441\u043e\u0432\u0440\u0435\u043c\u0435\u043d\u043d\u0430\u044f \u0442\u0435\u0445\u043d\u0438\u043a\u0430 http://t.co/E1uUtBi34s", "created_at": "Thu, 23 Apr 2015 05:35:05 +0000", "cntr_long": "United States", "day_report": "23/3/2015", "_links": {"self": {"href": "twittertop/5538848e591f908f2b8b83c8", "title": "Twittertop"}}, "loc_name": "Birmingham", "_created": "Thu, 01 Jan 1970 00:00:00 GMT", "_id": "5538848e591f908f2b8b83c8", "_etag": "1be9207c362f2c5248a586b49bfcd45f05b58f5f"}, {"cntr_short": "US", "city": "Norman", "_updated": "Thu, 01 Jan 1970 00:00:00 GMT", "loc": [35.2225668, -97.4394777], "text": "WoT #Blitz. \u041e\u0431\u0437\u043e\u0440 \u043e\u0431\u043d\u043e\u0432\u043b\u0435\u043d\u0438\u044f 1.8 http://t.co/OdLi5bgFsl #rtBYme #worldoftanks #android #facebook #twitter #wotblitz", "created_at": "Thu, 23 Apr 2015 05:34:56 +0000", "cntr_long": "United States", "day_report": "23/3/2015", "_links": {"self": {"href": "twittertop/553884899ad4ec3b478b8932", "title": "Twittertop"}}, "loc_name": "Norman, OK", "_created": "Thu, 01 Jan 1970 00:00:00 GMT", "_id": "553884899ad4ec3b478b8932", "_etag": "02514a5e927ace850282db3e0d28078563e24f7e"}, {"cntr_short": "US", "city": "Santee", "_updated": "Thu, 01 Jan 1970 00:00:00 GMT", "loc": [32.8383828, -116.9739167], "text": "@ShesSelenaUs @selenagomez I'm still with you on that 3rd WOWP movie..that would be great :)", "created_at": "Thu, 23 Apr 2015 05:33:19 +0000", "cntr_long": "United States", "day_report": "23/3/2015", "_links": {"self": {"href": "twittertop/5538843f9ad4ec9a228b4f0d", "title": "Twittertop"}}, "loc_name": "Santee,California", "_created": "Thu, 01 Jan 1970 00:00:00 GMT", "_id": "5538843f9ad4ec9a228b4f0d", "_etag": "101a8f3e4ef493e16bae8cb3fc331869dd3b848b"}, {"cntr_short": "US", "city": "Chicago", "_updated": "Thu, 01 Jan 1970 00:00:00 GMT", "loc": [41.8781136, -87.6297982], "text": "@dogcaptin haha no, &lt;30 is crawling with lvling bots... Worse than wowp vp sometimes", "created_at": "Thu, 23 Apr 2015 05:30:45 +0000", "cntr_long": "United States", "day_report": "23/3/2015", "_links": {"self": {"href": "twittertop/5538838e9ad4ec3f768b742d", "title": "Twittertop"}}, "loc_name": "Chicago, IL", "_created": "Thu, 01 Jan 1970 00:00:00 GMT", "_id": "5538838e9ad4ec3f768b742d", "_etag": "5dab405529ee52afac167ce616ee409e5dcbeb04"}, {"cntr_short": "BY", "city": "\u041a\u0440\u0438\u0432\u0441\u043a", "_updated": "Thu, 01 Jan 1970 00:00:00 GMT", "loc": [52.5880856, 30.5117037], "text": "\u0420\u0430\u0437\u0434\u0430\u0447\u0430 \u0438\u0433\u0440\u044b World of Tanks: Premium http://t.co/BmEb1PFXY1", "created_at": "Thu, 23 Apr 2015 05:29:22 +0000", "cntr_long": "Belarus", "day_report": "23/3/2015", "_links": {"self": {"href": "twittertop/55388339591f90ea398b74d9", "title": "Twittertop"}}, "loc_name": "\u041a\u0440\u0438\u0432\u0441\u043a", "_created": "Thu, 01 Jan 1970 00:00:00 GMT", "_id": "55388339591f90ea398b74d9", "_etag": "11b6db5ea4ee023b0a4023ae146d1a1edbb9f55c"}, {"cntr_short": "SK", "city": "Vysok\u00e9 Tatry", "_updated": "Thu, 01 Jan 1970 00:00:00 GMT", "loc": [49.18727029999999, 19.9338545], "text": "@Xbox Anybody know , when World of Tanks gona be on Xbox One :D I cant wait for that", "created_at": "Thu, 23 Apr 2015 05:28:35 +0000", "cntr_long": "Slovakia", "day_report": "23/3/2015", "_links": {"self": {"href": "twittertop/553883159ad4ec5c038b8663", "title": "Twittertop"}}, "loc_name": "Liptov", "_created": "Thu, 01 Jan 1970 00:00:00 GMT", "_id": "553883159ad4ec5c038b8663", "_etag": "1c2caa73dabf468d5d4c2eb440908d020a6166bb"}, {"cntr_short": "RU", "city": "Slavyanka", "_updated": "Thu, 01 Jan 1970 00:00:00 GMT", "loc": [42.8690697, 131.380371], "text": "\u041c\u043d\u0435 \u043f\u043e\u043d\u0440\u0430\u0432\u0438\u043b\u043e\u0441\u044c \u0432\u0438\u0434\u0435\u043e \"[\u041f\u0430\u0442\u0447 0.9.7] \u041c\u043e\u0434\u041f\u0430\u043a \u043e\u0442 PRO\u0422\u0430\u043d\u043a\u0438 | \u041c\u041e\u0414\u043d\u044b\u0435 \u043d\u043e\u0432\u0438\u043d\u043a\u0438 World of Tanks\"", "created_at": "Thu, 23 Apr 2015 05:27:12 +0000", "cntr_long": "Russia", "day_report": "23/3/2015", "_links": {"self": {"href": "twittertop/553882f19ad4ec4d6f8b4ede", "title": "Twittertop"}}, "loc_name": "42.868878,131.380842", "_created": "Thu, 01 Jan 1970 00:00:00 GMT", "_id": "553882f19ad4ec4d6f8b4ede", "_etag": "07561016e2f72052fb2bd1238df8038d178bda63"}, {"cntr_short": "RU", "city": "Vidnoye", "_updated": "Thu, 01 Jan 1970 00:00:00 GMT", "loc": [55.55, 37.7], "text": "Caernarvon - \u0413\u0430\u0439\u0434 \u043f\u043e World of Tanks - \u0421\u043a\u0440\u044b\u0442\u0430\u044f \u0421\u0438\u043b\u0430 \u0422\u04228 \u0411\u0440\u0438\u0442\u0430\u043d\u0438\u0438 https://t.co/s17qyErHgi", "created_at": "Thu, 23 Apr 2015 05:25:58 +0000", "cntr_long": "Russia", "day_report": "23/3/2015", "_links": {"self": {"href": "twittertop/55388283591f90e73e8b4cbe", "title": "Twittertop"}}, "loc_name": "\u0412\u0438\u0434\u043d\u043e\u0435", "_created": "Thu, 01 Jan 1970 00:00:00 GMT", "_id": "55388283591f90e73e8b4cbe", "_etag": "b4931ecef9ae3bc3f0bb20617b3a9607546d511a"}, {"cntr_short": "FR", "city": "Chahaignes", "_updated": "Thu, 01 Jan 1970 00:00:00 GMT", "loc": [47.727469, 0.512104], "text": "WoT Xbox http://t.co/DZnwghvcBf", "created_at": "Thu, 23 Apr 2015 05:17:06 +0000", "cntr_long": "France", "day_report": "23/3/2015", "_links": {"self": {"href": "twittertop/55388062591f900b478b4fee", "title": "Twittertop"}}, "loc_name": "\u3053\u3053", "_created": "Thu, 01 Jan 1970 00:00:00 GMT", "_id": "55388062591f900b478b4fee", "_etag": "823eb538e7293ad38c5f27f90169c82cfb1d0211"}, {"cntr_short": "JP", "city": " ", "_updated": "Thu, 01 Jan 1970 00:00:00 GMT", "loc": [35.6894875, 139.6917064], "text": "\u0410\u043a\u043a World Of Tanks \u0441 Type59 http://t.co/cqffZvMlw7 http://t.co/Uomr3VjU5R", "created_at": "Thu, 23 Apr 2015 05:14:08 +0000", "cntr_long": "Japan", "day_report": "23/3/2015", "_links": {"self": {"href": "twittertop/55387fd79ad4ec3c078b528a", "title": "Twittertop"}}, "loc_name": "\u6771\u4eac\u90fd", "_created": "Thu, 01 Jan 1970 00:00:00 GMT", "_id": "55387fd79ad4ec3c078b528a", "_etag": "a38daebea9199607228c844fb6559837e1ac68db"}, {"cntr_short": "UA", "city": "Donetsk", "_updated": "Thu, 01 Jan 1970 00:00:00 GMT", "loc": [48.015883, 37.80285], "text": "\u041c\u043d\u0435 \u043f\u043e\u043d\u0440\u0430\u0432\u0438\u043b\u043e\u0441\u044c \u0432\u0438\u0434\u0435\u043e \"WoT \u0443\u0440\u043e\u0434\u044b \u0412\u044b\u043f\u0443\u0441\u043a #69 ~World of Tanks (wot)\" (http://t.co/hCHaVokX1b)", "created_at": "Thu, 23 Apr 2015 05:12:44 +0000", "cntr_long": "Ukraine", "day_report": "23/3/2015", "_links": {"self": {"href": "twittertop/55387f50591f908e7e8b5c54", "title": "Twittertop"}}, "loc_name": "\u0414\u043e\u043d\u0435\u0446\u043a", "_created": "Thu, 01 Jan 1970 00:00:00 GMT", "_id": "55387f50591f908e7e8b5c54", "_etag": "60b2afacd2b08ccf330c71c6df5228df769ef8e4"}, {"cntr_short": "US", "city": "Norman", "_updated": "Thu, 01 Jan 1970 00:00:00 GMT", "loc": [35.2225668, -97.4394777], "text": "\u0421\u0442\u0440\u0438\u043c World of Tanks Blitz \u2013 \u0438\u0433\u0440\u0430\u0435\u043c \u0441\u043e \u0437\u0440\u0438\u0442\u0435\u043b\u044f\u043c\u0438 11.04.2015 \u0421\u0435\u0440\u0435\u0433\u0430 \u041a\u0440\u0430\u0431 http://t.co/2WW9wQUcRf #rtBYme #worldoftanks", "created_at": "Thu, 23 Apr 2015 05:11:56 +0000", "cntr_long": "United States", "day_report": "23/3/2015", "_links": {"self": {"href": "twittertop/55387f4b9ad4eca16f8b6160", "title": "Twittertop"}}, "loc_name": "Norman, OK", "_created": "Thu, 01 Jan 1970 00:00:00 GMT", "_id": "55387f4b9ad4eca16f8b6160", "_etag": "4006deedab1595374bac2b2bf7eeb1437c9ecca2"}, {"cntr_short": "SE", "city": "Malm\u00f6", "_updated": "Thu, 01 Jan 1970 00:00:00 GMT", "loc": [55.604981, 13.003822], "text": "Before work - World of Tanks or Ships. Average guy! #worldoftanks #wows: http://t.co/yJDIG3b5dJ", "created_at": "Thu, 23 Apr 2015 05:10:21 +0000", "cntr_long": "Sweden", "day_report": "23/3/2015", "_links": {"self": {"href": "twittertop/55387ec5591f908a7e8b5bbb", "title": "Twittertop"}}, "loc_name": "Malm\u00f6 / Sweden", "_created": "Thu, 01 Jan 1970 00:00:00 GMT", "_id": "55387ec5591f908a7e8b5bbb", "_etag": "719375c1b31eec8ae761e91899fe6f46828269ba"}, {"cntr_short": "UA", "city": "Kulynka", "_updated": "Thu, 01 Jan 1970 00:00:00 GMT", "loc": [49.145, 24.248611], "text": "World of Tanks \u0432\u043e\u0437\u043c\u043e\u0436\u043d\u043e \u043b\u0443\u0447\u0448\u0438\u0439 \u0431\u043e\u0439 \u0438\u0437 \u043f\u0430\u0442\u0447\u0430 0.9.6 wot \u043d\u0430\u0433\u0438\u0431 https://t.co/2FkbtjNBLE", "created_at": "Thu, 23 Apr 2015 05:04:26 +0000", "cntr_long": "Ukraine", "day_report": "23/3/2015", "_links": {"self": {"href": "twittertop/55387d6a591f90e73e8b4c9e", "title": "Twittertop"}}, "loc_name": "\u041a\u0443\u043b\u0438\u043d\u043a\u0430", "_created": "Thu, 01 Jan 1970 00:00:00 GMT", "_id": "55387d6a591f90e73e8b4c9e", "_etag": "a152492f1706f1ff29e7ec9a5ef776a273f33eee"}, {"cntr_short": "RU", "city": "Yaroslavl", "_updated": "Thu, 01 Jan 1970 00:00:00 GMT", "loc": [57.62607440000001, 39.8844708], "text": "\u0424\u0438\u043d\u0430\u043b \u043b\u0438\u0433\u0438 World of Tanks \u043f\u0440\u043e\u0439\u0434\u0435\u0442 25-26 \u0430\u043f\u0440\u0435\u043b\u044f http://t.co/WoK8VOsrrR", "created_at": "Thu, 23 Apr 2015 04:54:02 +0000", "cntr_long": "Russia", "day_report": "23/3/2015", "_links": {"self": {"href": "twittertop/55387b029ad4ecc00b8bae8a", "title": "Twittertop"}}, "loc_name": "\u042f\u0440\u043e\u0441\u043b\u0430\u0432\u043b\u044c", "_created": "Thu, 01 Jan 1970 00:00:00 GMT", "_id": "55387b029ad4ecc00b8bae8a", "_etag": "688966b3a3ef2bf5ccca60e02105af9d0d7508f9"}, {"cntr_short": "UA", "city": "Dnepropetrovsk", "_updated": "Thu, 01 Jan 1970 00:00:00 GMT", "loc": [48.464717, 35.046183], "text": "I liked a @YouTube video http://t.co/tg0aq3WWOO !!!_\u0421_\u0422_\u0420_\u0418_\u041c_!!!\u041f\u041e \u0418\u0413\u0420\u0415:-WORLD OF TANKS!", "created_at": "Thu, 23 Apr 2015 04:51:22 +0000", "cntr_long": "Ukraine", "day_report": "23/3/2015", "_links": {"self": {"href": "twittertop/55387a79591f900d678b5e7b", "title": "Twittertop"}}, "loc_name": "\u0414\u043d\u0435\u043f\u0440\u043e\u043f\u0435\u0442\u0440\u043e\u0432\u0441\u043a \u0423\u043a\u0440\u0430\u0438\u043d\u0430", "_created": "Thu, 01 Jan 1970 00:00:00 GMT", "_id": "55387a79591f900d678b5e7b", "_etag": "351f3d4d84dbe374fc8765afbdaeb3b21591ae3b"}, {"cntr_short": "UA", "city": "Kyiv", "_updated": "Thu, 01 Jan 1970 00:00:00 GMT", "loc": [50.4363485, 30.5560432], "text": "\u041f\u043e\u0434\u0440\u043e\u0431\u043d\u043e\u0441\u0442\u0438 \u043d\u043e\u0432\u043e\u0433\u043e \u043e\u0431\u043d\u043e\u0432\u043b\u0435\u043d\u0438\u044f World of Tanks http://t.co/znB5K8Ys9F #\u0438\u043d\u0444\u043e\u0440\u043c\u0430\u0446\u0438\u044f", "created_at": "Thu, 23 Apr 2015 04:50:14 +0000", "cntr_long": "Ukraine", "day_report": "23/3/2015", "_links": {"self": {"href": "twittertop/55387a0e591f908d0d8bc5f1", "title": "Twittertop"}}, "loc_name": "\u0423\u043a\u0440\u0430\u0457\u043d\u0430, All", "_created": "Thu, 01 Jan 1970 00:00:00 GMT", "_id": "55387a0e591f908d0d8bc5f1", "_etag": "a71f0a2f8ebf6ba38b4dc3e1a79fef47c236a543"}, {"cntr_short": "US", "city": "Norman", "_updated": "Thu, 01 Jan 1970 00:00:00 GMT", "loc": [35.2225668, -97.4394777], "text": "#World of Tanks Blitz HD Gameplay \u2013 M4 #Sherman Tank http://t.co/9BXQ6CKujg #rtBYme #worldoftanks #hdgameplay", "created_at": "Thu, 23 Apr 2015 04:50:03 +0000", "cntr_long": "United States", "day_report": "23/3/2015", "_links": {"self": {"href": "twittertop/55387a09591f9077398b519b", "title": "Twittertop"}}, "loc_name": "Norman, OK", "_created": "Thu, 01 Jan 1970 00:00:00 GMT", "_id": "55387a09591f9077398b519b", "_etag": "a84969a73742a39872d5a7a1d469f0ac5830253c"}, {"cntr_short": "BR", "city": "Ipatinga", "_updated": "Thu, 01 Jan 1970 00:00:00 GMT", "loc": [-19.4707569, -42.548012], "text": "Gostei de um v\u00eddeo @YouTube de @yt3coelhos http://t.co/DRl2hZmOWo WORLD OF TANKS \u2013 3K e Davy Jones EMBRAZADOS!", "created_at": "Thu, 23 Apr 2015 04:48:29 +0000", "cntr_long": "Brazil", "day_report": "23/3/2015", "_links": {"self": {"href": "twittertop/553879a69ad4ecdc1c8b5553", "title": "Twittertop"}}, "loc_name": "Ipatinga/MG", "_created": "Thu, 01 Jan 1970 00:00:00 GMT", "_id": "553879a69ad4ecdc1c8b5553", "_etag": "ac9a3bf1dfb78d10b5818136a87a131cb6ca94d0"}, {"cntr_short": "ID", "city": " ", "_updated": "Thu, 01 Jan 1970 00:00:00 GMT", "loc": [-0.789275, 113.921327], "text": "World of Warships Naval Academy: Torpedoes http://t.co/bAAwACWetk http://t.co/mmt3dEix2x", "created_at": "Thu, 23 Apr 2015 04:42:01 +0000", "cntr_long": "Indonesia", "day_report": "23/3/2015", "_links": {"self": {"href": "twittertop/55387840591f90567c8bbfd4", "title": "Twittertop"}}, "loc_name": "Indonesia", "_created": "Thu, 01 Jan 1970 00:00:00 GMT", "_id": "55387840591f90567c8bbfd4", "_etag": "4b27d051ff6ef545253b8928774af7305c6a58b6"}, {"cntr_short": "CA", "city": " ", "_updated": "Thu, 01 Jan 1970 00:00:00 GMT", "loc": [56.130366, -106.346771], "text": "I liked a @YouTube video from @mightyjingles http://t.co/eLyqALQVqR World of Tanks - From Russia With Love", "created_at": "Thu, 23 Apr 2015 04:37:54 +0000", "cntr_long": "Canada", "day_report": "23/3/2015", "_links": {"self": {"href": "twittertop/553877409ad4ec40348b4f44", "title": "Twittertop"}}, "loc_name": "Canada", "_created": "Thu, 01 Jan 1970 00:00:00 GMT", "_id": "553877409ad4ec40348b4f44", "_etag": "eb7c3a6bb42934c4e0f46ef071a577267cab9cca"}, {"cntr_short": "US", "city": " ", "_updated": "Thu, 01 Jan 1970 00:00:00 GMT", "loc": [31.9685988, -99.9018131], "text": "Meanwhile in World of Tanks... Ramming everything in my T-34. Ypaaaaa!", "created_at": "Thu, 23 Apr 2015 04:33:27 +0000", "cntr_long": "United States", "day_report": "23/3/2015", "_links": {"self": {"href": "twittertop/5538763a591f9044388b60ce", "title": "Twittertop"}}, "loc_name": "Yuriland, Texas, USA", "_created": "Thu, 01 Jan 1970 00:00:00 GMT", "_id": "5538763a591f9044388b60ce", "_etag": "6393c9b87dd8aa6da2290fd17e218927f1702aa4"}, {"cntr_short": "GB", "city": "Sunderland", "_updated": "Thu, 01 Jan 1970 00:00:00 GMT", "loc": [54.906869, -1.383801], "text": "I liked a @YouTube video from @cosmiccarrie123 http://t.co/Df0CJ214qm Cromwell gameplay (Tier VI British medium) (World of Tanks", "created_at": "Thu, 23 Apr 2015 04:26:18 +0000", "cntr_long": "United Kingdom", "day_report": "23/3/2015", "_links": {"self": {"href": "twittertop/5538747c591f90ff318b563d", "title": "Twittertop"}}, "loc_name": "sunderland,uk", "_created": "Thu, 01 Jan 1970 00:00:00 GMT", "_id": "5538747c591f90ff318b563d", "_etag": "981253388029d83593234a11817196408a7315ae"}, {"cntr_short": "UA", "city": "Voronivka", "_updated": "Thu, 01 Jan 1970 00:00:00 GMT", "loc": [47.668333, 31.423333], "text": "\u0412 World of Tanks \u043f\u0440\u0438\u0448\u043b\u0438 \u043f\u0435\u0440\u0432\u043e\u0430\u043f\u0440\u0435\u043b\u044c\u0441\u043a\u0438\u0435 \u0437\u043e\u043c\u0431\u0438", "created_at": "Thu, 23 Apr 2015 04:24:42 +0000", "cntr_long": "Ukraine", "day_report": "23/3/2015", "_links": {"self": {"href": "twittertop/5538740e591f90662b8b5538", "title": "Twittertop"}}, "loc_name": "\u0412\u043e\u0440\u043e\u043d\u043e\u0432\u043a\u0430", "_created": "Thu, 01 Jan 1970 00:00:00 GMT", "_id": "5538740e591f90662b8b5538", "_etag": "b126c94ff19592162293fbad46f8670a3d56fe77"}, {"cntr_short": "US", "city": "Norman", "_updated": "Thu, 01 Jan 1970 00:00:00 GMT", "loc": [35.2225668, -97.4394777], "text": "#World of #Tanks #Blitz \u2013 M4 Review http://t.co/TUfKganYot #rtBYme #worldoftanks #people #tanksblitz", "created_at": "Thu, 23 Apr 2015 04:20:49 +0000", "cntr_long": "United States", "day_report": "23/3/2015", "_links": {"self": {"href": "twittertop/5538735a591f90e43e8b4a6e", "title": "Twittertop"}}, "loc_name": "Norman, OK", "_created": "Thu, 01 Jan 1970 00:00:00 GMT", "_id": "5538735a591f90e43e8b4a6e", "_etag": "04ff6b0b5099d42bef42149af00fe8c0e1fb1ee0"}, {"cntr_short": "UA", "city": "Krushynka", "_updated": "Thu, 01 Jan 1970 00:00:00 GMT", "loc": [50.230556, 30.369722], "text": "World Of Tanks. \u042d\u0442\u043e T57 Heavy Tank https://t.co/SWraL4Vqfw", "created_at": "Thu, 23 Apr 2015 04:16:42 +0000", "cntr_long": "Ukraine", "day_report": "23/3/2015", "_links": {"self": {"href": "twittertop/553872309ad4ec2d0c8b5971", "title": "Twittertop"}}, "loc_name": "\u041a\u0440\u0443\u0448\u0438\u043d\u043a\u0430", "_created": "Thu, 01 Jan 1970 00:00:00 GMT", "_id": "553872309ad4ec2d0c8b5971", "_etag": "2d10d163f4165d4df899ad1f57c36158ec6cb692"}, {"cntr_short": "JP", "city": "\u583a\u5e02", "_updated": "Thu, 01 Jan 1970 00:00:00 GMT", "loc": [34.5298443, 135.4939759], "text": "\u6e7e\u5cb8\u30df\u30c3\u30c9\u30ca\u30a4\u30c8/ToLOVE\u308b-\u30c0\u30fc\u30af\u30cd\u30b9-/\u30ef\u30f3\u30d1\u30f3\u30de\u30f3/\u30c9\u30e9\u30b4\u30f3\u30dc\u30fc\u30eb/WorldofTanks/\u653b\u6bbb\u6a5f\u52d5\u968a(ARISE)\u3000#\u4e00\u3064\u3067\u3082\u597d\u304d\u306a\u3082\u306e\u3042\u3063\u305f\u3089RT #RT\u3057\u305f\u4eba\u5168\u54e1\u30d5\u30a9\u30ed\u30fc\u3059\u308b\u3000\u3042\u3001\u3061\u306a\u307f\u306b\u30c0\u30fc\u30af\u30cd\u30b9\u306f\u306b\u308f\u304b\u3067\u3059\u3002\u30e1\u30a2\u3061\u3083\u3093\u304b\u308f\u3044\u3044\u3088\u30e1\u30a2\u3061\u3083\u3093", "created_at": "Thu, 23 Apr 2015 04:02:33 +0000", "cntr_long": "Japan", "day_report": "23/3/2015", "_links": {"self": {"href": "twittertop/55386ef5591f90d5158b5474", "title": "Twittertop"}}, "loc_name": "\u6211\u304c\u5bb6", "_created": "Thu, 01 Jan 1970 00:00:00 GMT", "_id": "55386ef5591f90d5158b5474", "_etag": "fa64a2ee17c9fbbe7f96b39e72385080a514ba17"}, {"cntr_short": "US", "city": " ", "_updated": "Thu, 01 Jan 1970 00:00:00 GMT", "loc": [40.4172871, -82.90712300000001], "text": "Channel Update and the Quest for Yamato ( World of Warships ): http://t.co/Fbv5gPMP5Z via @YouTube", "created_at": "Thu, 23 Apr 2015 04:02:03 +0000", "cntr_long": "United States", "day_report": "23/3/2015", "_links": {"self": {"href": "twittertop/55386ed19ad4ec581e8b6263", "title": "Twittertop"}}, "loc_name": "Ohio, US", "_created": "Thu, 01 Jan 1970 00:00:00 GMT", "_id": "55386ed19ad4ec581e8b6263", "_etag": "1abc7576eb1df0c83beaafccde36d9f997deaf68"}, {"cntr_short": "US", "city": "Norman", "_updated": "Thu, 01 Jan 1970 00:00:00 GMT", "loc": [35.2225668, -97.4394777], "text": "World of Tanks BLITZ \u2013 #Jagdtiger 8.8cm Tier 8 #Premium German #Tank Destroyer. http://t.co/ce73r53cHv #rtBYme", "created_at": "Thu, 23 Apr 2015 03:52:26 +0000", "cntr_long": "United States", "day_report": "22/3/2015", "_links": {"self": {"href": "twittertop/55386c809ad4ecc63e8b5cf7", "title": "Twittertop"}}, "loc_name": "Norman, OK", "_created": "Thu, 01 Jan 1970 00:00:00 GMT", "_id": "55386c809ad4ecc63e8b5cf7", "_etag": "dd79a8f4036ff8856b763eaa50928cf8dffeee75"}, {"cntr_short": "US", "city": "New York", "_updated": "Thu, 01 Jan 1970 00:00:00 GMT", "loc": [40.7127837, -74.0059413], "text": "@GamerGirlEva True, they are working heavy on world of warships at the moment.", "created_at": "Thu, 23 Apr 2015 03:52:16 +0000", "cntr_long": "United States", "day_report": "22/3/2015", "_links": {"self": {"href": "twittertop/55386c809ad4ecc63e8b5cf6", "title": "Twittertop"}}, "loc_name": "New York", "_created": "Thu, 01 Jan 1970 00:00:00 GMT", "_id": "55386c809ad4ecc63e8b5cf6", "_etag": "bbe7369b9393d901dab556cb3a04b60eff472987"}, {"cntr_short": "MP", "city": " ", "_updated": "Thu, 01 Jan 1970 00:00:00 GMT", "loc": [16.616667, 145.616667], "text": "iOS\u7248 Blitz \u30a2\u30c3\u30d7\u30c7\u30fc\u30c8 1.8 \u9045\u5ef6\u306e\u304a\u77e5\u3089\u305b | \u30cb\u30e5\u30fc\u30b9 | World of Tanks Blitz http://t.co/vkgmLRp3Ts", "created_at": "Thu, 23 Apr 2015 03:49:17 +0000", "cntr_long": "Northern Mariana Islands", "day_report": "22/3/2015", "_links": {"self": {"href": "twittertop/55386bf0591f90d5158b53b4", "title": "Twittertop"}}, "loc_name": "\u30de\u30ea\u30a2\u30ca\u8af8\u5cf6", "_created": "Thu, 01 Jan 1970 00:00:00 GMT", "_id": "55386bf0591f90d5158b53b4", "_etag": "775438a135c3fb00d7956b92f8a1b5ab4eeb468a"}, {"cntr_short": "RU", "city": "Ryazan", "_updated": "Thu, 01 Jan 1970 00:00:00 GMT", "loc": [54.6095418, 39.7125857], "text": "\u041c\u044b \u0440\u0430\u0441\u0441\u043a\u0430\u0437\u0430\u043b\u0438, \u043a\u0430\u043a \u0438\u0433\u0440\u0430\u044e\u0442 \u0432 World of Tanks \u0442\u043e\u043f\u043e\u0432\u044b\u0435 \u043a\u043b\u0430\u043d\u044b http://t.co/blRtX85LnV", "created_at": "Thu, 23 Apr 2015 03:48:07 +0000", "cntr_long": "Russia", "day_report": "22/3/2015", "_links": {"self": {"href": "twittertop/55386bc79ad4ecb3198b65ce", "title": "Twittertop"}}, "loc_name": "\u0420\u044f\u0437\u0430\u043d\u044c", "_created": "Thu, 01 Jan 1970 00:00:00 GMT", "_id": "55386bc79ad4ecb3198b65ce", "_etag": "531b1745ba416a815470efb4448508296917cb5f"}, {"cntr_short": "DE", "city": "Berlin", "_updated": "Thu, 01 Jan 1970 00:00:00 GMT", "loc": [52.52000659999999, 13.404954], "text": "Ich habe ein @YouTube-Video von @eikarrramba positiv bewertet: http://t.co/HXBU2njAae World of Tanks - Together Gameplay | Lorraine", "created_at": "Thu, 23 Apr 2015 03:37:11 +0000", "cntr_long": "Germany", "day_report": "22/3/2015", "_links": {"self": {"href": "twittertop/553869059ad4ec9f728b5fa9", "title": "Twittertop"}}, "loc_name": "Berlin", "_created": "Thu, 01 Jan 1970 00:00:00 GMT", "_id": "553869059ad4ec9f728b5fa9", "_etag": "9efed87ba16af3af0820f3c4c48dccc10ded72f9"}, {"cntr_short": "GB", "city": "Peterborough", "_updated": "Thu, 01 Jan 1970 00:00:00 GMT", "loc": [52.57083129999999, -0.3006158], "text": "VIDEO: \u0438\u043d\u0432\u0430\u0439\u0442 \u043a\u043e\u0434 \u0434\u043b\u044f \u0431\u0435\u0442\u0430 \u0442\u0435\u0441\u0442\u0430 world of warships 2015 \u0410\u043f\u0440\u0435\u043b\u044c | Watch: http://t.co/XAHEWhRMbQ via Youtube", "created_at": "Thu, 23 Apr 2015 03:36:25 +0000", "cntr_long": "United Kingdom", "day_report": "22/3/2015", "_links": {"self": {"href": "twittertop/553868bc9ad4ecdb768b4a83", "title": "Twittertop"}}, "loc_name": "Worldwide", "_created": "Thu, 01 Jan 1970 00:00:00 GMT", "_id": "553868bc9ad4ecdb768b4a83", "_etag": "a05c2ba182c470a95970f98a86d07fbd46ef30a9"}, {"cntr_short": "GB", "city": "Peterborough", "_updated": "Thu, 01 Jan 1970 00:00:00 GMT", "loc": [52.57083129999999, -0.3006158], "text": "VIDEO: \u0438\u043d\u0432\u0430\u0439\u0442 \u043a\u043e\u0434 world of warships \u0446\u0438\u0442\u0430\u0434\u0435\u043b\u044c 2015 \u0410\u043f\u0440\u0435\u043b\u044c | Watch: http://t.co/IkhDoeetYv via Youtube", "created_at": "Thu, 23 Apr 2015 03:36:20 +0000", "cntr_long": "United Kingdom", "day_report": "22/3/2015", "_links": {"self": {"href": "twittertop/553868b79ad4eca16f8b5f71", "title": "Twittertop"}}, "loc_name": "Worldwide", "_created": "Thu, 01 Jan 1970 00:00:00 GMT", "_id": "553868b79ad4eca16f8b5f71", "_etag": "ef65d9200b6284a2493b71490119df95f57e5dea"}, {"cntr_short": "RU", "city": "Samara", "_updated": "Thu, 01 Jan 1970 00:00:00 GMT", "loc": [53.202778, 50.140833], "text": "[\u041f\u0430\u0442\u0447 0.9.7] \u041c\u043e\u0434\u041f\u0430\u043a \u043e\u0442 PRO\u0422\u0430\u043d\u043a\u0438 | \u041c\u041e\u0414\u043d\u044b\u0435 \u043d\u043e\u0432\u0438\u043d\u043a\u0438 World of Tanks https://t.co/XJKAyl9X2a \u0441 \u043f\u043e\u043c\u043e\u0449\u044c\u044e @YouTube", "created_at": "Thu, 23 Apr 2015 03:30:31 +0000", "cntr_long": "Russia", "day_report": "22/3/2015", "_links": {"self": {"href": "twittertop/55386789591f90d3228b6cd6", "title": "Twittertop"}}, "loc_name": "\u0421\u0430\u043c\u0430\u0440\u0430", "_created": "Thu, 01 Jan 1970 00:00:00 GMT", "_id": "55386789591f90d3228b6cd6", "_etag": "74f994c1d7472ed9a9be8c8d8b0a1a6820f424be"}, {"cntr_short": "US", "city": "Norman", "_updated": "Thu, 01 Jan 1970 00:00:00 GMT", "loc": [35.2225668, -97.4394777], "text": "#World Of #Tanks #Blitz: LUCKIEST RNG EVER!!! http://t.co/1yjgHrNB1e #rtBYme #worldoftanks #acount #tanksblitz", "created_at": "Thu, 23 Apr 2015 03:28:02 +0000", "cntr_long": "United States", "day_report": "22/3/2015", "_links": {"self": {"href": "twittertop/553866ec9ad4eca5728b59d4", "title": "Twittertop"}}, "loc_name": "Norman, OK", "_created": "Thu, 01 Jan 1970 00:00:00 GMT", "_id": "553866ec9ad4eca5728b59d4", "_etag": "75b390e55eea0ba624b37d6cc875a3d3bc1b748f"}, {"cntr_short": "JP", "city": "Ichinomiya", "_updated": "Thu, 01 Jan 1970 00:00:00 GMT", "loc": [35.3038899, 136.8029326], "text": "\u307e\u3058\u304b\u2026 iOS\u7248 Blitz \u30a2\u30c3\u30d7\u30c7\u30fc\u30c8 1.8 \u9045\u5ef6\u306e\u304a\u77e5\u3089\u305b | \u30cb\u30e5\u30fc\u30b9 | World of Tanks Blitz http://t.co/shfnZCWTrf", "created_at": "Thu, 23 Apr 2015 03:23:00 +0000", "cntr_long": "Japan", "day_report": "22/3/2015", "_links": {"self": {"href": "twittertop/5538659f9ad4ecc36a8b736b", "title": "Twittertop"}}, "loc_name": "Ichinomiya, Aichi, Japan", "_created": "Thu, 01 Jan 1970 00:00:00 GMT", "_id": "5538659f9ad4ecc36a8b736b", "_etag": "92d8fc4e0edd5d576fcc236e0e65b95310f13e4c"}, {"cntr_short": "JP", "city": "Matsue", "_updated": "Thu, 01 Jan 1970 00:00:00 GMT", "loc": [35.4680595, 133.048375], "text": "World of Tanks Blitz\u3000android\u7248\u304c\u51fa\u3066\u610f\u6c17\u63da\u3005\u3068\u30a4\u30f3\u30b9\u30c8\u30fc\u30eb\u3057\u3088\u3046\u3068\u601d\u3063\u305f\u3089\u3001\u5bfe\u5fdc\u6a5f\u7a2e\u5916\u3067\u672a\u3060\u306b\u904a\u3079\u3066\u3044\u306a\u3044\u3002\u3000#World of Tanks Blitz", "created_at": "Thu, 23 Apr 2015 03:18:50 +0000", "cntr_long": "Japan", "day_report": "22/3/2015", "_links": {"self": {"href": "twittertop/553864c19ad4ec034a8b581c", "title": "Twittertop"}}, "loc_name": "\u5cf6\u6839\u770c\u677e\u6c5f\u5e02", "_created": "Thu, 01 Jan 1970 00:00:00 GMT", "_id": "553864c19ad4ec034a8b581c", "_etag": "989c8aed6d15bedc51dbf61638a71114c97b4c41"}, {"cntr_short": "UA", "city": "Bylbasivka", "_updated": "Thu, 01 Jan 1970 00:00:00 GMT", "loc": [48.8394872, 37.5001624], "text": "\u041d\u0430\u0437\u0432\u0430\u043d\u044b \u0443\u0447\u0430\u0441\u0442\u043d\u0438\u043a\u0438 \u0444\u0438\u043d\u0430\u043b\u0430 \u043f\u043e World of Tanks \u0441\u0440\u0435\u0434\u0438 \u043a\u043e\u043c\u0430\u043d\u0434 \u0420\u043e\u0441\u0441\u0438\u0438 \u0438 \u0421\u041d\u0413", "created_at": "Thu, 23 Apr 2015 03:17:44 +0000", "cntr_long": "Ukraine", "day_report": "22/3/2015", "_links": {"self": {"href": "twittertop/553864739ad4ecf5678b4bf4", "title": "Twittertop"}}, "loc_name": "\u0411\u044b\u043b\u0431\u0430\u0441\u043e\u0432\u043a\u0430", "_created": "Thu, 01 Jan 1970 00:00:00 GMT", "_id": "553864739ad4ecf5678b4bf4", "_etag": "9c3a0d75c09000095a3e85ef36f37e32785d8b9d"}], "_links": {"self": {"href": "twittertop?max_results=50", "title": "twittertop"}, "last": {"href": "twittertop?max_results=50&page=2", "title": "last page"}, "parent": {"href": "/", "title": "home"}, "next": {"href": "twittertop?max_results=50&page=2", "title": "next page"}}, "_meta": {"max_results": 50, "total": 79, "page": 1}}